[
  {
    "full_name": "anomalyco/opencode",
    "stargazers_count": 160423,
    "open_issues_count": 6229,
    "forks_count": 18807
  },
  {
    "full_name": "FULU-Foundation/CRW-Extension",
    "stargazers_count": 868,
    "open_issues_count": 14,
    "forks_count": 29
  },
  {
    "full_name": "soteria-infra/soteria-sdk",
    "stargazers_count": 34,
    "open_issues_count": 0,
    "forks_count": 1
  },
  {
    "full_name": "AlienUI-Org/AlienUI",
    "stargazers_count": 202,
    "open_issues_count": 7,
    "forks_count": 7
  },
  {
    "full_name": "Python9ja/pynigeria-backend",
    "stargazers_count": 11,
    "open_issues_count": 11,
    "forks_count": 12
  },
  {
    "full_name": "Python9ja/pynigeria",
    "stargazers_count": 8,
    "open_issues_count": 10,
    "forks_count": 7
  },
  {
    "full_name": "rustdesk/rustdesk",
    "stargazers_count": 114212,
    "open_issues_count": 111,
    "forks_count": 17160
  },
  {
    "full_name": "realworld-angular/realworld-angular",
    "stargazers_count": 117,
    "open_issues_count": 2,
    "forks_count": 6
  },
  {
    "full_name": "KillerCodeMonkey/ngx-quill",
    "stargazers_count": 1850,
    "open_issues_count": 6,
    "forks_count": 273
  },
  {
    "full_name": "withfig/fig",
    "stargazers_count": 2019,
    "open_issues_count": 738,
    "forks_count": 65
  },
  {
    "full_name": "johnkomarnicki/vue-3-crash-course",
    "stargazers_count": 47,
    "open_issues_count": 0,
    "forks_count": 38
  },
  {
    "full_name": "Oluwatemmy/Link-Ease",
    "stargazers_count": 2,
    "open_issues_count": 0,
    "forks_count": 1
  },
  {
    "full_name": "Unique-Red/url_shortner",
    "stargazers_count": 7,
    "open_issues_count": 1,
    "forks_count": 3
  },
  {
    "full_name": "Kabari/Scissor",
    "stargazers_count": 1,
    "open_issues_count": 0,
    "forks_count": 1
  },
  {
    "full_name": "Veektaw/Snip-API",
    "stargazers_count": 3,
    "open_issues_count": 0,
    "forks_count": 0
  },
  {
    "full_name": "reactive-python/reactpy",
    "stargazers_count": 8136,
    "open_issues_count": 53,
    "forks_count": 328
  },
  {
    "full_name": "Olatisunkanmi/nigeria-geo",
    "stargazers_count": 4,
    "open_issues_count": 0,
    "forks_count": 1
  },
  {
    "full_name": "googlemaps/google-maps-services-python",
    "stargazers_count": 4945,
    "open_issues_count": 71,
    "forks_count": 1348
  },
  {
    "full_name": "microsoft/AI-For-Beginners",
    "stargazers_count": 47509,
    "open_issues_count": 4,
    "forks_count": 9815
  },
  {
    "full_name": "bobby-didcoding/drf_course",
    "stargazers_count": 291,
    "open_issues_count": 10,
    "forks_count": 254
  },
  {
    "full_name": "titiodus/dizzy-eggz",
    "stargazers_count": 43,
    "open_issues_count": 3,
    "forks_count": 10
  },
  {
    "full_name": "github/gitignore",
    "stargazers_count": 173906,
    "open_issues_count": 71,
    "forks_count": 82543
  },
  {
    "full_name": "pytest-dev/pytest",
    "stargazers_count": 13852,
    "open_issues_count": 987,
    "forks_count": 3130
  },
  {
    "full_name": "ifeoluwatomiii/space-kangaroo",
    "stargazers_count": 3,
    "open_issues_count": 0,
    "forks_count": 0
  },
  {
    "full_name": "CalebEmelike/flask-pizza-api",
    "stargazers_count": 5,
    "open_issues_count": 0,
    "forks_count": 5
  },
  {
    "full_name": "wadelu23/basic-RESTful-flask-e-store",
    "stargazers_count": 5,
    "open_issues_count": 0,
    "forks_count": 2
  },
  {
    "full_name": "realpython/materials",
    "stargazers_count": 5157,
    "open_issues_count": 81,
    "forks_count": 5306
  },
  {
    "full_name": "microsoft/AcademicContent",
    "stargazers_count": 2793,
    "open_issues_count": 0,
    "forks_count": 959
  },
  {
    "full_name": "prakhar1989/docker-curriculum",
    "stargazers_count": 6041,
    "open_issues_count": 94,
    "forks_count": 2223
  },
  {
    "full_name": "freeCodeCamp/freeCodeCamp",
    "stargazers_count": 444749,
    "open_issues_count": 195,
    "forks_count": 44574
  }
]